binance_aio/__init__.py
binance_aio/__version__.py
binance_aio/authentication.py
binance_aio/binance_rest_auth.py
binance_aio/binance_ws_async.py
binance_aio/binance_ws_userdata.py
binance_aio/error.py
binance_aio/util.py
binance_aio/websocket_test.py
binance_ws_async-0.1.1.dist-info/LICENSE
binance_ws_async-0.1.1.dist-info/METADATA
binance_ws_async-0.1.1.dist-info/WHEEL
binance_ws_async-0.1.1.dist-info/top_level.txt
binance_ws_async-0.1.1.dist-info/zip-safe
binance_ws_async-0.1.1.dist-info/RECORD
